[
  {
    "id": 1,
    "name": "Channel 1",
    "type": "youtube",
    "url": "https://www.youtube.com/embed/SWQXGhWohy0?si=YATvL67_rSpr4QJU",
    "title": "YouTube Stream",
    "description": "Embedded YouTube stream provided by admin.",
    "autoplay": false
  },
  {
    "id": 2,
    "name": "Channel 2 - Hope Channel",
    "type": "hls",
    "url": "https://videodelivery.net/9fb3596948ddf463fde0ec4b85625b24/manifest/video.m3u8",
    "title": "Christian Broadcasting",
    "description": "Christian IPTV source from the uploaded IPTV master list.",
    "autoplay": false
  },
  {
    "id": 3,
    "name": "Channel 3 - Daystar TV",
    "type": "hls",
    "url": "https://live-mcl.cdn01.net/smarttv/48vy43564/playlist.m3u8",
    "title": "Christian Broadcasting",
    "description": "Christian IPTV source from the uploaded IPTV master list.",
    "autoplay": false
  },
  {
    "id": 4,
    "name": "Channel 4 - 3ABN Canada",
    "type": "hls",
    "url": "https://3abn.bozztv.com/3abncanada/3ABN/master.m3u8",
    "title": "Christian Broadcasting",
    "description": "Christian IPTV source from the uploaded IPTV master list.",
    "autoplay": false
  },
  {
    "id": 5,
    "name": "Channel 5 - Gospel Movie TV",
    "type": "hls",
    "url": "https://stmv1.srvif.com/gospelf/gospelf/playlist.m3u8",
    "title": "Christian Broadcasting",
    "description": "Christian IPTV source from the uploaded IPTV master list.",
    "autoplay": false
  },
  {
    "id": 6,
    "name": "Channel 6 - GOD TV",
    "type": "hls",
    "url": "https://ott.god.tv/live/us/master.m3u8",
    "title": "Christian Broadcasting",
    "description": "Christian IPTV source from the uploaded IPTV master list.",
    "autoplay": false
  },
  {
    "id": 7,
    "name": "Channel 7 - History & Warfare",
    "type": "hls",
    "url": "https://d28gzbv9fhdm3h.cloudfront.net/playlist/amg00376-magellantv-historyandwar",
    "title": "Documentary",
    "description": "Documentary IPTV source from the uploaded IPTV master list.",
    "autoplay": false
  },
  {
    "id": 8,
    "name": "Channel 8 - PBS Science",
    "type": "hls",
    "url": "https://amg02333-pbs-amg02333c13-samsung-au-6858.playouts.now.amagi.tv/playlist.m3u8",
    "title": "Documentary",
    "description": "Documentary IPTV source from the uploaded IPTV master list.",
    "autoplay": false
  },
  {
    "id": 9,
    "name": "Channel 9 - Sky News Arabia",
    "type": "hls",
    "url": "https://stream.skynewsarabia.com/ott/ott.m3u8",
    "title": "News",
    "description": "News IPTV source from the uploaded IPTV master list.",
    "autoplay": false
  },
  {
    "id": 10,
    "name": "Channel 10 - EWTN International",
    "type": "hls",
    "url": "https://cdn3.wowza.com/1/ZVBYYXFLLzE0c3NC/Qk1FMURC/hls/live/playlist.m3u8",
    "title": "International Christian Channel",
    "description": "International Christian IPTV source from the uploaded IPTV master list.",
    "autoplay": false
  },
  {
    "id": 11,
    "name": "Channel 11 - Fox Weather",
    "type": "hls",
    "url": "https://247wlive.foxweather.com/stream/index.m3u8",
    "title": "Weather Channel",
    "description": "Weather IPTV source from the uploaded IPTV master list.",
    "autoplay": false
  }
]